{"manifestVersion":"1.1","info":{"id":"FTPUpload.0cec898d-2d66-4be5-899e-c0f8788695cc,version=1.0","manifestType":"Extension"},"packages":[{"id":"Component.FTPUpload.0cec898d-2d66-4be5-899e-c0f8788695cc","version":"1.0","type":"Component","extension":true,"dependencies":{"FTPUpload.0cec898d-2d66-4be5-899e-c0f8788695cc":"1.0","Microsoft.VisualStudio.Component.CoreEditor":"[15.0,17.0)"},"localizedResources":[{"language":"en-US","title":"FTPUpload","description":"Empty VSIX Project."}]},{"id":"FTPUpload.0cec898d-2d66-4be5-899e-c0f8788695cc","version":"1.0","type":"Vsix","payloads":[{"fileName":"FTPUpload.vsix","size":473711}],"vsixId":"FTPUpload.0cec898d-2d66-4be5-899e-c0f8788695cc","extensionDir":"[installdir]\\Common7\\IDE\\Extensions\\m2wdqzll.veh","installSizes":{"targetDrive":468536}}]}